hivetrace/__init__.py
hivetrace/adapters/__init__.py
hivetrace/adapters/base_adapter.py
hivetrace/adapters/crewai/__init__.py
hivetrace/adapters/crewai/adapter.py
hivetrace/adapters/crewai/decorators.py
hivetrace/adapters/crewai/monitored_agent.py
hivetrace/adapters/crewai/monitored_crew.py
hivetrace/adapters/crewai/tool_wrapper.py
hivetrace/adapters/langchain/__init__.py
hivetrace/adapters/langchain/adapter.py
hivetrace/adapters/langchain/api.py
hivetrace/adapters/langchain/behavior_tracker.py
hivetrace/adapters/langchain/callback.py
hivetrace/adapters/langchain/decorators.py
hivetrace/adapters/langchain/models.py
hivetrace/adapters/openai_agents/__init__.py
hivetrace/adapters/openai_agents/adapter.py
hivetrace/adapters/openai_agents/models.py
hivetrace/adapters/openai_agents/tracing.py
hivetrace/adapters/utils/__init__.py
hivetrace/adapters/utils/logging.py
hivetrace/client/__init__.py
hivetrace/client/async_client.py
hivetrace/client/base.py
hivetrace/client/sync_client.py
hivetrace/errors/__init__.py
hivetrace/errors/api.py
hivetrace/errors/base.py
hivetrace/errors/network.py
hivetrace/errors/validation.py
hivetrace/handlers/__init__.py
hivetrace/handlers/error_handler.py
hivetrace/handlers/response_builder.py
hivetrace/models/__init__.py
hivetrace/models/requests.py
hivetrace/models/responses.py
hivetrace/utils/__init__.py
hivetrace/utils/error_helpers.py
hivetrace/utils/uuid_generator.py
hivetrace-1.3.10.dist-info/LICENSE
hivetrace-1.3.10.dist-info/METADATA
hivetrace-1.3.10.dist-info/WHEEL
hivetrace-1.3.10.dist-info/top_level.txt
hivetrace-1.3.10.dist-info/RECORD
