Metadata-Version: 2.1
Name: hivetrace
Version: 1.3.10
Summary: Hivetrace SDK for monitoring LLM applications
Home-page: http://hivetrace.ai
Author: Raft
Author-email: sales@raftds.com
Keywords: SDK,monitoring,logging,LLM,AI,Hivetrace
Classifier: License :: OSI Approved :: Apache Software License
Requires-Python: >=3.8
License-File: LICENSE
Requires-Dist: httpx >=0.28.1
Requires-Dist: pydantic >=2.11.7
Requires-Dist: python-dotenv >=1.0.1
Provides-Extra: all
Requires-Dist: crewai >=0.95.0 ; extra == 'all'
Requires-Dist: httpx >=0.28.1 ; extra == 'all'
Requires-Dist: langchain-community ==0.3.18 ; extra == 'all'
Requires-Dist: langchain-openai ==0.2.5 ; extra == 'all'
Requires-Dist: langchain ==0.3.19 ; extra == 'all'
Requires-Dist: langchain-experimental ==0.3.4 ; extra == 'all'
Requires-Dist: openai-agents >=0.1.0 ; extra == 'all'
Requires-Dist: pydantic >=2.11.7 ; extra == 'all'
Requires-Dist: python-dotenv >=1.0.1 ; extra == 'all'
Provides-Extra: base
Requires-Dist: httpx >=0.28.1 ; extra == 'base'
Requires-Dist: pydantic >=2.11.7 ; extra == 'base'
Requires-Dist: python-dotenv >=1.0.1 ; extra == 'base'
Provides-Extra: crewai
Requires-Dist: crewai >=0.95.0 ; extra == 'crewai'
Provides-Extra: langchain
Requires-Dist: langchain-community ==0.3.18 ; extra == 'langchain'
Requires-Dist: langchain-openai ==0.2.5 ; extra == 'langchain'
Requires-Dist: langchain ==0.3.19 ; extra == 'langchain'
Requires-Dist: langchain-experimental ==0.3.4 ; extra == 'langchain'
Provides-Extra: openai_agents
Requires-Dist: openai-agents >=0.1.0 ; extra == 'openai_agents'
